MANIFEST.in
README.rst
setup.py
aliyunsdkr_kvstore/__init__.py
aliyunsdkr_kvstore/request/__init__.py
aliyunsdkr_kvstore/request/v20150101/CreateBackupRequest.py
aliyunsdkr_kvstore/request/v20150101/CreateInstanceRequest.py
aliyunsdkr_kvstore/request/v20150101/CreateSnapshotRequest.py
aliyunsdkr_kvstore/request/v20150101/CreateStaticVerificationRequest.py
aliyunsdkr_kvstore/request/v20150101/CreateTempInstanceRequest.py
aliyunsdkr_kvstore/request/v20150101/DeleteInstanceRequest.py
aliyunsdkr_kvstore/request/v20150101/DeleteSnapshotRequest.py
aliyunsdkr_kvstore/request/v20150101/DeleteSnapshotSettingsRequest.py
aliyunsdkr_kvstore/request/v20150101/DeleteTempInstanceRequest.py
aliyunsdkr_kvstore/request/v20150101/DescribeBackupPolicyRequest.py
aliyunsdkr_kvstore/request/v20150101/DescribeBackupsRequest.py
aliyunsdkr_kvstore/request/v20150101/DescribeCertificationRequest.py
aliyunsdkr_kvstore/request/v20150101/DescribeDBInstanceNetInfoRequest.py
aliyunsdkr_kvstore/request/v20150101/DescribeHistoryMonitorValuesRequest.py
aliyunsdkr_kvstore/request/v20150101/DescribeInstanceAttributeRequest.py
aliyunsdkr_kvstore/request/v20150101/DescribeInstanceConfigRequest.py
aliyunsdkr_kvstore/request/v20150101/DescribeInstanceSSLRequest.py
aliyunsdkr_kvstore/request/v20150101/DescribeInstancesByExpireTimeRequest.py
aliyunsdkr_kvstore/request/v20150101/DescribeInstancesRequest.py
aliyunsdkr_kvstore/request/v20150101/DescribeLogicInstanceTopologyRequest.py
aliyunsdkr_kvstore/request/v20150101/DescribeMonitorItemsRequest.py
aliyunsdkr_kvstore/request/v20150101/DescribeMonthlyServiceStatusDetailRequest.py
aliyunsdkr_kvstore/request/v20150101/DescribeMonthlyServiceStatusRequest.py
aliyunsdkr_kvstore/request/v20150101/DescribeRdsVSwitchsRequest.py
aliyunsdkr_kvstore/request/v20150101/DescribeRdsVpcsRequest.py
aliyunsdkr_kvstore/request/v20150101/DescribeRegionsRequest.py
aliyunsdkr_kvstore/request/v20150101/DescribeReplicaConflictInfoRequest.py
dd_aliyun_python_sdk_r_kvstore.egg-info/PKG-INFO
dd_aliyun_python_sdk_r_kvstore.egg-info/SOURCES.txt
dd_aliyun_python_sdk_r_kvstore.egg-info/dependency_links.txt
dd_aliyun_python_sdk_r_kvstore.egg-info/requires.txt
dd_aliyun_python_sdk_r_kvstore.egg-info/top_level.txt